{
  "kingdom": 221,
  "last_updated": "2026-04-16",
  "source": "ADB screenshot scraper + EasyOCR extraction",
  "categories": {
    "alliance_power": [
      {
        "rank": 1,
        "tag": "TPM",
        "name": "Peacemakers",
        "value": 17829932612
      },
      {
        "rank": 2,
        "tag": "GLO",
        "name": "DwarvesUprising",
        "value": 15320752258
      },
      {
        "rank": 3,
        "tag": "SXY",
        "name": "SmashAndGrab",
        "value": 12118092250
      },
      {
        "rank": 4,
        "tag": "BLD",
        "name": "Bloodline",
        "value": 11316488744
      },
      {
        "rank": 5,
        "tag": "LIC",
        "name": "FingerLickinGood",
        "value": 2916777834
      },
      {
        "rank": 6,
        "tag": "GNz",
        "name": "TheZenith",
        "value": 2131962917
      },
      {
        "rank": 7,
        "tag": "gLo",
        "name": "GlobalAcademy",
        "value": 2092028236
      },
      {
        "rank": 8,
        "tag": "BLH",
        "name": "BloodyHell",
        "value": 1618514067
      },
      {
        "rank": 9,
        "tag": "JIB",
        "name": "Enigmatic",
        "value": 1584395857
      },
      {
        "rank": 10,
        "tag": "FTx",
        "name": "TheAvengers",
        "value": 1424922421
      },
      {
        "rank": 11,
        "tag": "Kor",
        "name": "KOREtt",
        "value": 1107365521
      },
      {
        "rank": 12,
        "tag": "SFO",
        "name": "ShadowFangOrder",
        "value": 1027267207
      },
      {
        "rank": 13,
        "tag": "GOL",
        "name": "GuardiansofLight",
        "value": 568452217
      },
      {
        "rank": 14,
        "tag": "HvK",
        "name": "Misfits",
        "value": 400856658
      },
      {
        "rank": 15,
        "tag": "Mjj",
        "name": "SithLords",
        "value": 384505204
      },
      {
        "rank": 16,
        "tag": "ZXF",
        "name": "AlphaSquad",
        "value": 308017574
      },
      {
        "rank": 17,
        "tag": "",
        "name": "",
        "value": 284068566
      },
      {
        "rank": 18,
        "tag": "GYo",
        "name": "Gurtyo",
        "value": 231682192
      },
      {
        "rank": 19,
        "tag": "mxt",
        "name": "HyruleKingdom",
        "value": 174320284
      },
      {
        "rank": 20,
        "tag": "wYtll",
        "name": "eon14",
        "value": 165970098
      },
      {
        "rank": 21,
        "tag": "DDS",
        "name": "DailyDose",
        "value": 157618205
      },
      {
        "rank": 22,
        "tag": "FRM",
        "name": "OnlyFarms",
        "value": 143002233
      },
      {
        "rank": 23,
        "tag": "hsR",
        "name": "KingdomHyrule",
        "value": 124485126
      },
      {
        "rank": 24,
        "tag": "",
        "name": "",
        "value": 114944534
      },
      {
        "rank": 25,
        "tag": "",
        "name": "",
        "value": 104662037
      },
      {
        "rank": 26,
        "tag": "",
        "name": "",
        "value": 96594230
      },
      {
        "rank": 27,
        "tag": "GTX",
        "name": "Eternos",
        "value": 96594230
      },
      {
        "rank": 28,
        "tag": "xDx",
        "name": "WarGamesHQD",
        "value": 91522134
      },
      {
        "rank": 29,
        "tag": "xAx",
        "name": "WarGamesHQA",
        "value": 86086492
      },
      {
        "rank": 30,
        "tag": "NWO",
        "name": "KnightsXTemplar",
        "value": 85411390
      },
      {
        "rank": 31,
        "tag": "POL",
        "name": "AktywniPL",
        "value": 79863220
      },
      {
        "rank": 32,
        "tag": "VOgIv",
        "name": "Og",
        "value": 78578738
      },
      {
        "rank": 33,
        "tag": "Zajl",
        "name": "KillYourHeroes",
        "value": 74881261
      },
      {
        "rank": 34,
        "tag": "Usa",
        "name": "EmpireofAAZEL",
        "value": 72228338
      },
      {
        "rank": 35,
        "tag": "",
        "name": "",
        "value": 67533381
      },
      {
        "rank": 36,
        "tag": "NOP",
        "name": "NewOnePiece",
        "value": 67019945
      },
      {
        "rank": 37,
        "tag": "ROc",
        "name": "ROC214",
        "value": 66929244
      },
      {
        "rank": 38,
        "tag": "MXX",
        "name": "MexicoLATAM",
        "value": 64749689
      },
      {
        "rank": 39,
        "tag": "JWpls",
        "name": "onsofassarchy",
        "value": 61742976
      },
      {
        "rank": 40,
        "tag": "gwJ",
        "name": "Brazucas",
        "value": 61633556
      },
      {
        "rank": 41,
        "tag": "Dc",
        "name": "HailHail67",
        "value": 60450123
      },
      {
        "rank": 42,
        "tag": "MBA",
        "name": "MajinBooArea",
        "value": 59719497
      },
      {
        "rank": 43,
        "tag": "",
        "name": "",
        "value": 56738225
      },
      {
        "rank": 44,
        "tag": "888",
        "name": "#A@ (ExF>Zem)",
        "value": 56715161
      },
      {
        "rank": 45,
        "tag": "Xxx",
        "name": "xxx214",
        "value": 53074959
      },
      {
        "rank": 46,
        "tag": "KBA",
        "name": "KidBuuArea",
        "value": 52016308
      },
      {
        "rank": 47,
        "tag": "CDw",
        "name": "Friday",
        "value": 51457501
      },
      {
        "rank": 48,
        "tag": "One",
        "name": "VNI",
        "value": 50803787
      },
      {
        "rank": 49,
        "tag": "KOR",
        "name": "AH2E9H",
        "value": 47784407
      },
      {
        "rank": 50,
        "tag": "MAD",
        "name": "MadHatters",
        "value": 46929634
      },
      {
        "rank": 51,
        "tag": "nYf",
        "name": "Abs",
        "value": 46141342
      },
      {
        "rank": 52,
        "tag": "",
        "name": "",
        "value": 44067776
      },
      {
        "rank": 53,
        "tag": "BoG",
        "name": "LikeVogButNot",
        "value": 44067776
      },
      {
        "rank": 54,
        "tag": "HOB",
        "name": "HouseofBICH",
        "value": 41487299
      },
      {
        "rank": 55,
        "tag": "LTS",
        "name": "LITTLES",
        "value": 40531770
      },
      {
        "rank": 56,
        "tag": "BEc",
        "name": "World",
        "value": 40417420
      },
      {
        "rank": 57,
        "tag": "GNH",
        "name": "Glendhiem",
        "value": 38512499
      },
      {
        "rank": 58,
        "tag": "GBW",
        "name": "DestinyFR",
        "value": 37350525
      },
      {
        "rank": 59,
        "tag": "LoD",
        "name": "LodFarmalliance",
        "value": 33746359
      },
      {
        "rank": 60,
        "tag": "zTe",
        "name": "Syd",
        "value": 32764114
      },
      {
        "rank": 61,
        "tag": "DPR",
        "name": "BUBARKANDPR",
        "value": 32206504
      },
      {
        "rank": 62,
        "tag": "Kqa",
        "name": "AllePanza",
        "value": 31567813
      },
      {
        "rank": 63,
        "tag": "CFvja",
        "name": "ntirebellion",
        "value": 30793906
      },
      {
        "rank": 64,
        "tag": "",
        "name": "",
        "value": 30304439
      },
      {
        "rank": 65,
        "tag": "",
        "name": "",
        "value": 29773451
      },
      {
        "rank": 66,
        "tag": "",
        "name": "",
        "value": 29466883
      },
      {
        "rank": 67,
        "tag": "",
        "name": "",
        "value": 28882393
      },
      {
        "rank": 68,
        "tag": "",
        "name": "",
        "value": 26078295
      },
      {
        "rank": 69,
        "tag": "",
        "name": "",
        "value": 24488308
      },
      {
        "rank": 70,
        "tag": "Glo",
        "name": "FermedeGLO",
        "value": 19297655
      },
      {
        "rank": 71,
        "tag": "OOo",
        "name": "WIN",
        "value": 19138487
      },
      {
        "rank": 72,
        "tag": "asg",
        "name": "NewFrontier",
        "value": 18802143
      },
      {
        "rank": 73,
        "tag": "PLD",
        "name": "PEACELAND",
        "value": 18449237
      },
      {
        "rank": 74,
        "tag": "EMP",
        "name": "Empire",
        "value": 17868336
      },
      {
        "rank": 75,
        "tag": "HCY",
        "name": "LouSkunt",
        "value": 16978749
      },
      {
        "rank": 76,
        "tag": "xCx",
        "name": "WarGamesHQC",
        "value": 16540458
      },
      {
        "rank": 77,
        "tag": "",
        "name": "",
        "value": 16021496
      },
      {
        "rank": 78,
        "tag": "",
        "name": "",
        "value": 15945980
      },
      {
        "rank": 79,
        "tag": "LTK",
        "name": "LATINKINGS",
        "value": 15263081
      },
      {
        "rank": 80,
        "tag": "LOL",
        "name": "PartyCrashers",
        "value": 15100393
      },
      {
        "rank": 81,
        "tag": "LHD",
        "name": "LederHosenDooD",
        "value": 14673229
      },
      {
        "rank": 82,
        "tag": "KzR",
        "name": "HearthBearers",
        "value": 14214963
      },
      {
        "rank": 83,
        "tag": "Naqlt",
        "name": "uRKiYE",
        "value": 13694271
      },
      {
        "rank": 84,
        "tag": "zBF",
        "name": "SkyEagleGang",
        "value": 13510842
      },
      {
        "rank": 85,
        "tag": "",
        "name": "",
        "value": 13438223
      },
      {
        "rank": 86,
        "tag": "",
        "name": "",
        "value": 13063164
      },
      {
        "rank": 87,
        "tag": "AZA",
        "name": "LordMRC",
        "value": 12967328
      },
      {
        "rank": 88,
        "tag": "DJT",
        "name": "Ensemble",
        "value": 12888671
      },
      {
        "rank": 89,
        "tag": "aVb",
        "name": "God",
        "value": 12438519
      },
      {
        "rank": 90,
        "tag": "aVb",
        "name": "GoD",
        "value": 12438519
      },
      {
        "rank": 91,
        "tag": "KGh",
        "name": "Uuy",
        "value": 11927657
      },
      {
        "rank": 92,
        "tag": "vDk",
        "name": "LordAYS",
        "value": 11717027
      },
      {
        "rank": 93,
        "tag": "YNM",
        "name": "DFg",
        "value": 11588146
      },
      {
        "rank": 94,
        "tag": "Zzzlg",
        "name": "eek",
        "value": 11248264
      },
      {
        "rank": 95,
        "tag": "LOd",
        "name": "LODRespekt234",
        "value": 11223277
      },
      {
        "rank": 96,
        "tag": "",
        "name": "",
        "value": 11044027
      },
      {
        "rank": 97,
        "tag": "bHw",
        "name": "SDCXFII",
        "value": 11044027
      },
      {
        "rank": 98,
        "tag": "msk",
        "name": "MASKED",
        "value": 10917568
      },
      {
        "rank": 99,
        "tag": "KFC",
        "name": "TIDBIT",
        "value": 10763044
      },
      {
        "rank": 100,
        "tag": "",
        "name": "Alliance Power",
        "value": 0
      }
    ],
    "alliance_kills": [
      {
        "rank": 1,
        "tag": "BLD",
        "name": "Bloodline",
        "value": 830240340
      },
      {
        "rank": 2,
        "tag": "SXY",
        "name": "SmashAndGrab",
        "value": 755625396
      },
      {
        "rank": 3,
        "tag": "TPM",
        "name": "Peacemakers",
        "value": 608322094
      },
      {
        "rank": 4,
        "tag": "GLO",
        "name": "DwarvesUprising",
        "value": 353812819
      },
      {
        "rank": 5,
        "tag": "LIC",
        "name": "FingerLickinGood",
        "value": 37053385
      },
      {
        "rank": 6,
        "tag": "BoY",
        "name": "CoolGuysOnly",
        "value": 15161436
      },
      {
        "rank": 7,
        "tag": "gLo",
        "name": "GlobalAcademy",
        "value": 14463712
      },
      {
        "rank": 8,
        "tag": "GNz",
        "name": "TheZenith",
        "value": 11360298
      },
      {
        "rank": 9,
        "tag": "FTx",
        "name": "TheAvengers",
        "value": 11088667
      },
      {
        "rank": 10,
        "tag": "JIB",
        "name": "Enigmatic",
        "value": 10779501
      },
      {
        "rank": 11,
        "tag": "BLH",
        "name": "BloodyHell",
        "value": 9422604
      },
      {
        "rank": 12,
        "tag": "GOL",
        "name": "GuardiansofLight",
        "value": 7345735
      },
      {
        "rank": 13,
        "tag": "Kor",
        "name": "KORHtt",
        "value": 6594323
      },
      {
        "rank": 14,
        "tag": "SFO",
        "name": "ShadowFangOrder",
        "value": 5873844
      },
      {
        "rank": 15,
        "tag": "Los",
        "name": "LastOnesStanding",
        "value": 1946244
      },
      {
        "rank": 16,
        "tag": "mxt",
        "name": "HyruleKingdom",
        "value": 1558260
      },
      {
        "rank": 17,
        "tag": "ZXF",
        "name": "AlphaSquad",
        "value": 1023568
      },
      {
        "rank": 18,
        "tag": "MAD",
        "name": "MadHatters",
        "value": 981077
      },
      {
        "rank": 19,
        "tag": "Zaj",
        "name": "KillYourHeroes",
        "value": 637983
      },
      {
        "rank": 20,
        "tag": "CDw",
        "name": "Friday",
        "value": 615793
      },
      {
        "rank": 21,
        "tag": "GYo",
        "name": "Gurtyo",
        "value": 566671
      },
      {
        "rank": 22,
        "tag": "FRM",
        "name": "OnlyFarms",
        "value": 416418
      },
      {
        "rank": 23,
        "tag": "FrM",
        "name": "221Farm",
        "value": 406951
      },
      {
        "rank": 24,
        "tag": "xAx",
        "name": "WarGamesHQA",
        "value": 400695
      },
      {
        "rank": 25,
        "tag": "MBA",
        "name": "MajinBooArea",
        "value": 335916
      },
      {
        "rank": 26,
        "tag": "VOgI",
        "name": "Og",
        "value": 323961
      },
      {
        "rank": 27,
        "tag": "HCYI",
        "name": "LouSkunt",
        "value": 321532
      },
      {
        "rank": 28,
        "tag": "HvK",
        "name": "Misfits",
        "value": 291409
      },
      {
        "rank": 29,
        "tag": "XwY",
        "name": "HoneyBadger",
        "value": 288932
      },
      {
        "rank": 30,
        "tag": "xDx",
        "name": "WarGamesHQD",
        "value": 283286
      },
      {
        "rank": 31,
        "tag": "REP",
        "name": "PREY",
        "value": 271471
      },
      {
        "rank": 32,
        "tag": "KOR",
        "name": "PH2H9H",
        "value": 260655
      },
      {
        "rank": 33,
        "tag": "POL",
        "name": "AktywniPL",
        "value": 237191
      },
      {
        "rank": 34,
        "tag": "Usa",
        "name": "EmpireofAAZEL",
        "value": 196500
      },
      {
        "rank": 35,
        "tag": "ROc",
        "name": "ROC214",
        "value": 196087
      },
      {
        "rank": 36,
        "tag": "Ftc",
        "name": "Marshal",
        "value": 193604
      },
      {
        "rank": 37,
        "tag": "888",
        "name": "#A #@ (27+YZ#m)",
        "value": 162500
      },
      {
        "rank": 38,
        "tag": "KBA",
        "name": "KidBuuArea",
        "value": 145304
      },
      {
        "rank": 39,
        "tag": "hsR",
        "name": "KingdomHyrule",
        "value": 138781
      },
      {
        "rank": 40,
        "tag": "HOB",
        "name": "HouseofBICH",
        "value": 136400
      },
      {
        "rank": 41,
        "tag": "Dc",
        "name": "JHailHail67",
        "value": 125418
      },
      {
        "rank": 42,
        "tag": "MXX",
        "name": "MexicoLATAM",
        "value": 120523
      },
      {
        "rank": 43,
        "tag": "GTX",
        "name": "Eternos",
        "value": 113696
      },
      {
        "rank": 44,
        "tag": "KFC",
        "name": "TIDBIT",
        "value": 108581
      },
      {
        "rank": 45,
        "tag": "xBx",
        "name": "WarGamesHQB",
        "value": 108507
      },
      {
        "rank": 46,
        "tag": "PLD",
        "name": "PEACELAND",
        "value": 105002
      },
      {
        "rank": 47,
        "tag": "HoG",
        "name": "WholetoGlory",
        "value": 98197
      },
      {
        "rank": 48,
        "tag": "NOP",
        "name": "NewOnePiece",
        "value": 97658
      },
      {
        "rank": 49,
        "tag": "LOL",
        "name": "PartyCrashers",
        "value": 96533
      },
      {
        "rank": 50,
        "tag": "CHN",
        "name": "AAEA (3+>2FmJ)",
        "value": 96185
      },
      {
        "rank": 51,
        "tag": "nrt",
        "name": "Justbuildnowar",
        "value": 91890
      },
      {
        "rank": 52,
        "tag": "ZKI",
        "name": "Zwergenkonige",
        "value": 91167
      },
      {
        "rank": 53,
        "tag": "GBW",
        "name": "DestinyFR",
        "value": 85857
      },
      {
        "rank": 54,
        "tag": "NIX",
        "name": "Phoenix",
        "value": 84585
      },
      {
        "rank": 55,
        "tag": "FzZ",
        "name": "SAT",
        "value": 82486
      },
      {
        "rank": 56,
        "tag": "GNH",
        "name": "Glendhiem",
        "value": 75346
      },
      {
        "rank": 57,
        "tag": "LTS",
        "name": "LITTLES",
        "value": 70588
      },
      {
        "rank": 58,
        "tag": "SGc",
        "name": "TLMN",
        "value": 67905
      },
      {
        "rank": 59,
        "tag": "gw",
        "name": "JJBrazucas",
        "value": 63470
      },
      {
        "rank": 60,
        "tag": "BEc",
        "name": "World",
        "value": 62766
      },
      {
        "rank": 61,
        "tag": "DDE",
        "name": "GermanDE",
        "value": 59468
      },
      {
        "rank": 62,
        "tag": "Qp",
        "name": "Xlvili",
        "value": 56585
      },
      {
        "rank": 63,
        "tag": "JWpls",
        "name": "onsofassarchy",
        "value": 56260
      },
      {
        "rank": 64,
        "tag": "",
        "name": "",
        "value": 54668
      },
      {
        "rank": 65,
        "tag": "jsf",
        "name": "? 4",
        "value": 53624
      },
      {
        "rank": 66,
        "tag": "iMe",
        "name": "Ederis",
        "value": 50161
      },
      {
        "rank": 67,
        "tag": "Naqlt",
        "name": "uRKiYE",
        "value": 43543
      },
      {
        "rank": 68,
        "tag": "OMG",
        "name": "kingdark",
        "value": 42077
      },
      {
        "rank": 69,
        "tag": "CFv",
        "name": "antirebellion",
        "value": 41439
      },
      {
        "rank": 70,
        "tag": "RVL",
        "name": "REVOLUTIONARY",
        "value": 39363
      },
      {
        "rank": 71,
        "tag": "DMD",
        "name": "ALAYA",
        "value": 37815
      },
      {
        "rank": 72,
        "tag": "zBF",
        "name": "SkyEagle",
        "value": 32670
      },
      {
        "rank": 73,
        "tag": "LoD",
        "name": "odFarmalliance",
        "value": 30487
      },
      {
        "rank": 74,
        "tag": "EXC",
        "name": "ExorcistID",
        "value": 27234
      },
      {
        "rank": 75,
        "tag": "OOo",
        "name": "WIN",
        "value": 26096
      },
      {
        "rank": 76,
        "tag": "wtB",
        "name": "Mystics",
        "value": 25945
      },
      {
        "rank": 77,
        "tag": "ekw",
        "name": "LordDestan",
        "value": 24230
      },
      {
        "rank": 78,
        "tag": "",
        "name": "",
        "value": 24081
      },
      {
        "rank": 79,
        "tag": "Oso",
        "name": "Alianzaimperial",
        "value": 24081
      },
      {
        "rank": 80,
        "tag": "ROK",
        "name": "RidersofKing",
        "value": 22661
      },
      {
        "rank": 81,
        "tag": "EMP",
        "name": "Empire",
        "value": 21871
      },
      {
        "rank": 82,
        "tag": "asg",
        "name": "NewFrontier",
        "value": 20245
      },
      {
        "rank": 83,
        "tag": "SPqli",
        "name": "mperialista",
        "value": 20219
      },
      {
        "rank": 84,
        "tag": "ECW",
        "name": "Chileanway",
        "value": 19751
      },
      {
        "rank": 85,
        "tag": "Rhn",
        "name": "independence",
        "value": 19677
      },
      {
        "rank": 86,
        "tag": "Rhn",
        "name": "Independence",
        "value": 19677
      },
      {
        "rank": 87,
        "tag": "SHM",
        "name": "SecondHandMass",
        "value": 19489
      },
      {
        "rank": 88,
        "tag": "DDS",
        "name": "DailyDose",
        "value": 4235
      },
      {
        "rank": 89,
        "tag": "BoG",
        "name": "LikeVogButNot",
        "value": 1284
      },
      {
        "rank": 90,
        "tag": "",
        "name": "Alliance Kills",
        "value": 0
      },
      {
        "rank": 91,
        "tag": "",
        "name": "Alance",
        "value": 0
      },
      {
        "rank": 92,
        "tag": "",
        "name": "Ivvuaia",
        "value": 0
      },
      {
        "rank": 93,
        "tag": "zTe",
        "name": "Syd",
        "value": 0
      },
      {
        "rank": 94,
        "tag": "",
        "name": "TJzU",
        "value": 0
      },
      {
        "rank": 95,
        "tag": "wxb",
        "name": "Asgon",
        "value": 0
      },
      {
        "rank": 96,
        "tag": "CQz",
        "name": "Darren8166",
        "value": 0
      },
      {
        "rank": 97,
        "tag": "SPali",
        "name": "mperialista",
        "value": 0
      },
      {
        "rank": 98,
        "tag": "EcWI",
        "name": "Chileanway",
        "value": 0
      }
    ],
    "personal_power": [
      {
        "rank": 1,
        "tag": "SXY",
        "name": "Cody4136",
        "value": 521830139
      },
      {
        "rank": 2,
        "tag": "BLD",
        "name": "FeeZPlay",
        "value": 496081477
      },
      {
        "rank": 3,
        "tag": "TPM",
        "name": "Lady Basia",
        "value": 400236371
      },
      {
        "rank": 4,
        "tag": "TPM",
        "name": "TSnell",
        "value": 382322648
      },
      {
        "rank": 5,
        "tag": "SXY",
        "name": "The Don Hugo",
        "value": 375508228
      },
      {
        "rank": 6,
        "tag": "TPM",
        "name": "Aidil Sfar",
        "value": 375325586
      },
      {
        "rank": 7,
        "tag": "TPM",
        "name": "Blackyy",
        "value": 354995422
      },
      {
        "rank": 8,
        "tag": "BLD",
        "name": "GLADIATOR",
        "value": 346187456
      },
      {
        "rank": 9,
        "tag": "BLD",
        "name": "Pups",
        "value": 342851067
      },
      {
        "rank": 10,
        "tag": "",
        "name": "XBLDJPups",
        "value": 342851067
      },
      {
        "rank": 11,
        "tag": "TPM",
        "name": "Jxl? Gaara",
        "value": 338846161
      },
      {
        "rank": 12,
        "tag": "GLO",
        "name": "AlexTheGreat",
        "value": 334725903
      },
      {
        "rank": 13,
        "tag": "BLD",
        "name": "DreadPirateGuntr",
        "value": 332052169
      },
      {
        "rank": 14,
        "tag": "BLD",
        "name": "MiffyOadis",
        "value": 329951188
      },
      {
        "rank": 15,
        "tag": "",
        "name": "",
        "value": 326529375
      },
      {
        "rank": 16,
        "tag": "",
        "name": "",
        "value": 324938154
      },
      {
        "rank": 17,
        "tag": "",
        "name": "",
        "value": 314304828
      },
      {
        "rank": 18,
        "tag": "",
        "name": "",
        "value": 313363341
      },
      {
        "rank": 19,
        "tag": "TPM",
        "name": "Double A",
        "value": 313363341
      },
      {
        "rank": 20,
        "tag": "",
        "name": "Hybrid Stalker",
        "value": 312149828
      },
      {
        "rank": 21,
        "tag": "",
        "name": "ITPMJSir Xant",
        "value": 309704658
      },
      {
        "rank": 22,
        "tag": "BLD",
        "name": "Jbrav ST",
        "value": 308677968
      },
      {
        "rank": 23,
        "tag": "SXY",
        "name": "kace",
        "value": 307709130
      },
      {
        "rank": 24,
        "tag": "BLD",
        "name": "Phlyx",
        "value": 302731704
      },
      {
        "rank": 25,
        "tag": "GLO",
        "name": "MadLuck",
        "value": 301164343
      },
      {
        "rank": 26,
        "tag": "GLO",
        "name": "Compal",
        "value": 296725559
      },
      {
        "rank": 27,
        "tag": "",
        "name": "",
        "value": 296127445
      },
      {
        "rank": 28,
        "tag": "HvK",
        "name": "Havok",
        "value": 293704057
      },
      {
        "rank": 29,
        "tag": "GLO",
        "name": "Foxconn",
        "value": 292823499
      },
      {
        "rank": 30,
        "tag": "BLD",
        "name": "Denyut Denyut",
        "value": 290105403
      },
      {
        "rank": 31,
        "tag": "GLO",
        "name": "Yniss",
        "value": 289067443
      },
      {
        "rank": 32,
        "tag": "TPM",
        "name": "Waffle",
        "value": 288068436
      },
      {
        "rank": 33,
        "tag": "BLD",
        "name": "Callisto",
        "value": 286256224
      },
      {
        "rank": 34,
        "tag": "",
        "name": "",
        "value": 286114405
      },
      {
        "rank": 35,
        "tag": "",
        "name": "",
        "value": 284856996
      },
      {
        "rank": 36,
        "tag": "GLO",
        "name": "IIEE@",
        "value": 275013774
      },
      {
        "rank": 37,
        "tag": "GLO",
        "name": "Arthur Dayne",
        "value": 274036750
      },
      {
        "rank": 38,
        "tag": "GLO",
        "name": "Deltamon",
        "value": 273876199
      },
      {
        "rank": 39,
        "tag": "TPM",
        "name": "Wadyk",
        "value": 272179024
      },
      {
        "rank": 40,
        "tag": "SXY",
        "name": "Maple",
        "value": 271082174
      },
      {
        "rank": 41,
        "tag": "",
        "name": "",
        "value": 270946723
      },
      {
        "rank": 42,
        "tag": "",
        "name": "",
        "value": 269414785
      },
      {
        "rank": 43,
        "tag": "",
        "name": "",
        "value": 264979945
      },
      {
        "rank": 44,
        "tag": "BLD",
        "name": "KhaosQween?",
        "value": 260148441
      },
      {
        "rank": 45,
        "tag": "BLD",
        "name": "saniku",
        "value": 259229896
      },
      {
        "rank": 46,
        "tag": "TPM",
        "name": "tmax",
        "value": 257753064
      },
      {
        "rank": 47,
        "tag": "TPM",
        "name": "Clark",
        "value": 253818660
      },
      {
        "rank": 48,
        "tag": "TPM",
        "name": "zIIE 22ZRED ribbon",
        "value": 251807637
      },
      {
        "rank": 49,
        "tag": "TPM",
        "name": "Two More Beers",
        "value": 251533164
      },
      {
        "rank": 50,
        "tag": "BLD",
        "name": "Ambrother",
        "value": 251499605
      },
      {
        "rank": 51,
        "tag": "gLO",
        "name": "NotMad",
        "value": 248926780
      },
      {
        "rank": 52,
        "tag": "gLo",
        "name": "NotMad",
        "value": 248926780
      },
      {
        "rank": 53,
        "tag": "GLO",
        "name": "Radamanthys",
        "value": 248775716
      },
      {
        "rank": 54,
        "tag": "BLD",
        "name": "Grandar",
        "value": 247091531
      },
      {
        "rank": 55,
        "tag": "TPM",
        "name": "Marko 73",
        "value": 246705957
      },
      {
        "rank": 56,
        "tag": "TPM",
        "name": "Pho Dac Biet",
        "value": 245063437
      },
      {
        "rank": 57,
        "tag": "BLD",
        "name": "Holiva",
        "value": 244517595
      },
      {
        "rank": 58,
        "tag": "TPM",
        "name": "Aiman Sfar",
        "value": 244280549
      },
      {
        "rank": 59,
        "tag": "TPM",
        "name": "LobaTheCute",
        "value": 243032407
      },
      {
        "rank": 60,
        "tag": "",
        "name": "",
        "value": 242545074
      },
      {
        "rank": 61,
        "tag": "TPM",
        "name": "dslsmoke",
        "value": 242063865
      },
      {
        "rank": 62,
        "tag": "SXY",
        "name": "Master Kosha",
        "value": 241230665
      },
      {
        "rank": 63,
        "tag": "TPM",
        "name": "ABADDY",
        "value": 241169135
      },
      {
        "rank": 64,
        "tag": "BLD",
        "name": "candy",
        "value": 239646114
      },
      {
        "rank": 65,
        "tag": "SXY",
        "name": "IKat",
        "value": 239006020
      },
      {
        "rank": 66,
        "tag": "SXY",
        "name": "TERA",
        "value": 237365890
      },
      {
        "rank": 67,
        "tag": "",
        "name": "",
        "value": 236905301
      },
      {
        "rank": 68,
        "tag": "",
        "name": "",
        "value": 236792295
      },
      {
        "rank": 69,
        "tag": "",
        "name": "",
        "value": 236435871
      },
      {
        "rank": 70,
        "tag": "BLD",
        "name": "Sal",
        "value": 235930334
      },
      {
        "rank": 71,
        "tag": "TPM",
        "name": "J JJB",
        "value": 233358668
      },
      {
        "rank": 72,
        "tag": "",
        "name": "IGLOJsabbiolina",
        "value": 232308616
      },
      {
        "rank": 73,
        "tag": "BLD",
        "name": "Ragnar Lothbrok",
        "value": 231817907
      },
      {
        "rank": 74,
        "tag": "BLD",
        "name": "Kela",
        "value": 229948448
      },
      {
        "rank": 75,
        "tag": "GLO",
        "name": "PunishmentofGod",
        "value": 229831155
      },
      {
        "rank": 76,
        "tag": "TPM",
        "name": "Lady McCor",
        "value": 229519076
      },
      {
        "rank": 77,
        "tag": "",
        "name": "",
        "value": 229003340
      },
      {
        "rank": 78,
        "tag": "",
        "name": "",
        "value": 227666745
      },
      {
        "rank": 79,
        "tag": "GLO",
        "name": "AKZ",
        "value": 227485720
      },
      {
        "rank": 80,
        "tag": "BLD",
        "name": "Mawi",
        "value": 226794688
      },
      {
        "rank": 81,
        "tag": "TPM",
        "name": "Dipset",
        "value": 226681968
      },
      {
        "rank": 82,
        "tag": "SXY",
        "name": "Elsbethos",
        "value": 226046935
      },
      {
        "rank": 83,
        "tag": "GLO",
        "name": "Jandel",
        "value": 225897306
      },
      {
        "rank": 84,
        "tag": "TPM",
        "name": "MiloPeng",
        "value": 225667031
      },
      {
        "rank": 85,
        "tag": "",
        "name": "Blaze",
        "value": 225648780
      },
      {
        "rank": 86,
        "tag": "",
        "name": "",
        "value": 225345981
      },
      {
        "rank": 87,
        "tag": "BLD",
        "name": "Rashmi",
        "value": 224980718
      },
      {
        "rank": 88,
        "tag": "BLD",
        "name": "Taz Man",
        "value": 224566204
      },
      {
        "rank": 89,
        "tag": "BLD",
        "name": "Tipsy",
        "value": 223772603
      },
      {
        "rank": 90,
        "tag": "SXY",
        "name": "Gardale",
        "value": 223690847
      },
      {
        "rank": 91,
        "tag": "SXY",
        "name": "IGardale",
        "value": 223690847
      },
      {
        "rank": 92,
        "tag": "TPM",
        "name": "Fawaz",
        "value": 222203377
      },
      {
        "rank": 93,
        "tag": "GLO",
        "name": "Raja",
        "value": 221816517
      },
      {
        "rank": 94,
        "tag": "GLo",
        "name": "Raja",
        "value": 221816517
      },
      {
        "rank": 95,
        "tag": "",
        "name": "",
        "value": 221263109
      },
      {
        "rank": 96,
        "tag": "",
        "name": "",
        "value": 221153488
      },
      {
        "rank": 97,
        "tag": "GLO",
        "name": "AII Mighty Nigel",
        "value": 221153488
      },
      {
        "rank": 98,
        "tag": "",
        "name": "",
        "value": 219541139
      },
      {
        "rank": 99,
        "tag": "GLO",
        "name": "Ennoconn",
        "value": 219541139
      },
      {
        "rank": 100,
        "tag": "BLD",
        "name": "Casira",
        "value": 215304676
      }
    ],
    "kill_count": [
      {
        "rank": 1,
        "tag": "SXY",
        "name": "Cody4136",
        "value": 205934371
      },
      {
        "rank": 2,
        "tag": "BLD",
        "name": "Jbrav ST",
        "value": 98630754
      },
      {
        "rank": 3,
        "tag": "BLD",
        "name": "FeeZPlay",
        "value": 92921636
      },
      {
        "rank": 4,
        "tag": "XBLD",
        "name": "Pups",
        "value": 84125279
      },
      {
        "rank": 5,
        "tag": "BLD",
        "name": "MiffyOadis",
        "value": 51904760
      },
      {
        "rank": 6,
        "tag": "TPM",
        "name": "Blackyy",
        "value": 45392478
      },
      {
        "rank": 7,
        "tag": "SXY",
        "name": "Queen Milfshakes",
        "value": 45345776
      },
      {
        "rank": 8,
        "tag": "SXY",
        "name": "kace",
        "value": 44977994
      },
      {
        "rank": 9,
        "tag": "GLO",
        "name": "MadLuck",
        "value": 44051857
      },
      {
        "rank": 10,
        "tag": "",
        "name": "SXYJZ IY A D",
        "value": 41657182
      },
      {
        "rank": 11,
        "tag": "BLD",
        "name": "DreadPirateGuntr",
        "value": 40695876
      },
      {
        "rank": 12,
        "tag": "TPM",
        "name": "Jxl? Gaara",
        "value": 40010498
      },
      {
        "rank": 13,
        "tag": "SXY",
        "name": "The Don Hugo",
        "value": 36362018
      },
      {
        "rank": 14,
        "tag": "BLD",
        "name": "Phlyx",
        "value": 35216035
      },
      {
        "rank": 15,
        "tag": "SXY",
        "name": "IBri A genoux",
        "value": 34477942
      },
      {
        "rank": 16,
        "tag": "SXY",
        "name": "IKat",
        "value": 27649824
      },
      {
        "rank": 17,
        "tag": "TPM",
        "name": "PrincessGold",
        "value": 27565143
      },
      {
        "rank": 18,
        "tag": "GLO",
        "name": "Foxconn",
        "value": 27437144
      },
      {
        "rank": 19,
        "tag": "TPM",
        "name": "TSnell",
        "value": 27306396
      },
      {
        "rank": 20,
        "tag": "TPM",
        "name": "Lady Basia",
        "value": 27087324
      },
      {
        "rank": 21,
        "tag": "SXY",
        "name": "Spartan",
        "value": 25944590
      },
      {
        "rank": 22,
        "tag": "GLO",
        "name": "Compal",
        "value": 25938643
      },
      {
        "rank": 23,
        "tag": "BLD",
        "name": "Tipsy Tappy",
        "value": 24966416
      },
      {
        "rank": 24,
        "tag": "SXY",
        "name": "Levi Foxtrott",
        "value": 24614602
      },
      {
        "rank": 25,
        "tag": "BLD",
        "name": "CrazyNotDeadYet",
        "value": 24123248
      },
      {
        "rank": 26,
        "tag": "SXY",
        "name": "Casanova 777",
        "value": 23700599
      },
      {
        "rank": 27,
        "tag": "BLD",
        "name": "Callisto",
        "value": 23397501
      },
      {
        "rank": 28,
        "tag": "BLD",
        "name": "Jables The Great",
        "value": 22466552
      },
      {
        "rank": 29,
        "tag": "TPM",
        "name": "Aidil Sfar",
        "value": 22203343
      },
      {
        "rank": 30,
        "tag": "SXY",
        "name": "GovRaden",
        "value": 22039262
      },
      {
        "rank": 31,
        "tag": "TPM",
        "name": "Kenth",
        "value": 21564666
      },
      {
        "rank": 32,
        "tag": "SXY",
        "name": "Gardale",
        "value": 21408490
      },
      {
        "rank": 33,
        "tag": "GLO",
        "name": "Ennoconn",
        "value": 20270659
      },
      {
        "rank": 34,
        "tag": "",
        "name": "",
        "value": 19474594
      },
      {
        "rank": 35,
        "tag": "TP",
        "name": "Miyb ?  RRTEtMTAWL",
        "value": 19422002
      },
      {
        "rank": 36,
        "tag": "TPM",
        "name": "?II= 22ZRED ribbon",
        "value": 18944721
      },
      {
        "rank": 37,
        "tag": "",
        "name": "Hybrid Stalker",
        "value": 18342973
      },
      {
        "rank": 38,
        "tag": "LIC",
        "name": "EMBERB",
        "value": 18035418
      },
      {
        "rank": 39,
        "tag": "GLO",
        "name": "PunishmentofGod",
        "value": 17546831
      },
      {
        "rank": 40,
        "tag": "TPM",
        "name": "KKYU_%3",
        "value": 17259847
      },
      {
        "rank": 41,
        "tag": "BLD",
        "name": "Mawi_M",
        "value": 17068658
      },
      {
        "rank": 42,
        "tag": "SXY",
        "name": "Lonelyman",
        "value": 16984573
      },
      {
        "rank": 43,
        "tag": "BLD",
        "name": "TinyPumpkin Jojo",
        "value": 16707226
      },
      {
        "rank": 44,
        "tag": "BLD",
        "name": "Rossi",
        "value": 16319707
      },
      {
        "rank": 45,
        "tag": "SXY",
        "name": "ITERA",
        "value": 16147517
      },
      {
        "rank": 46,
        "tag": "BLD",
        "name": "N45",
        "value": 15935248
      },
      {
        "rank": 47,
        "tag": "",
        "name": "Dead",
        "value": 15916255
      },
      {
        "rank": 48,
        "tag": "BLD",
        "name": "Denyut Denyut",
        "value": 15560062
      },
      {
        "rank": 49,
        "tag": "BLD",
        "name": "KhaosQween?",
        "value": 15333341
      },
      {
        "rank": 50,
        "tag": "",
        "name": "Battle",
        "value": 14757241
      },
      {
        "rank": 51,
        "tag": "SXY",
        "name": "ITH E MA D KING",
        "value": 14706087
      },
      {
        "rank": 52,
        "tag": "BLD",
        "name": "Rashmi",
        "value": 14617455
      },
      {
        "rank": 53,
        "tag": "BLD",
        "name": "Ambrother",
        "value": 14287245
      },
      {
        "rank": 54,
        "tag": "TPM",
        "name": "Pho Dac Biet",
        "value": 14162757
      },
      {
        "rank": 55,
        "tag": "BLD",
        "name": "Grandar",
        "value": 14111317
      },
      {
        "rank": 56,
        "tag": "GLO",
        "name": "Teteyutu",
        "value": 13885923
      },
      {
        "rank": 57,
        "tag": "BOY",
        "name": "Jorkin Goob",
        "value": 13796717
      },
      {
        "rank": 58,
        "tag": "GLO",
        "name": "Arthur Dayne",
        "value": 13464682
      },
      {
        "rank": 59,
        "tag": "GLo",
        "name": "Raja",
        "value": 13062829
      },
      {
        "rank": 60,
        "tag": "",
        "name": "FawkNAP",
        "value": 12634097
      },
      {
        "rank": 61,
        "tag": "",
        "name": "MasterofPuppets",
        "value": 12527697
      },
      {
        "rank": 62,
        "tag": "SXY",
        "name": "Maple",
        "value": 12491691
      },
      {
        "rank": 63,
        "tag": "TPM",
        "name": "tmax",
        "value": 12453353
      },
      {
        "rank": 64,
        "tag": "TPM",
        "name": "Aiman Sfar",
        "value": 12422738
      },
      {
        "rank": 65,
        "tag": "",
        "name": "HAA",
        "value": 12396314
      },
      {
        "rank": 66,
        "tag": "BLD",
        "name": "Benimaru",
        "value": 12342743
      },
      {
        "rank": 67,
        "tag": "GLU",
        "name": "Mujtaba51214",
        "value": 12211269
      },
      {
        "rank": 68,
        "tag": "BLD",
        "name": "ze7o",
        "value": 12206233
      },
      {
        "rank": 69,
        "tag": "TPM",
        "name": "RAHET",
        "value": 11960921
      },
      {
        "rank": 70,
        "tag": "TPM",
        "name": "Perceval",
        "value": 11657357
      },
      {
        "rank": 71,
        "tag": "",
        "name": "",
        "value": 11465142
      },
      {
        "rank": 72,
        "tag": "",
        "name": "",
        "value": 11463954
      },
      {
        "rank": 73,
        "tag": "",
        "name": "",
        "value": 11308888
      },
      {
        "rank": 74,
        "tag": "",
        "name": "",
        "value": 11277404
      },
      {
        "rank": 75,
        "tag": "BLD",
        "name": "Kela",
        "value": 11249665
      },
      {
        "rank": 76,
        "tag": "SXY",
        "name": "OsTraL",
        "value": 11021467
      },
      {
        "rank": 77,
        "tag": "GLo",
        "name": "ljohno",
        "value": 11020460
      },
      {
        "rank": 78,
        "tag": "TPM",
        "name": "Duke Promethean",
        "value": 10481516
      },
      {
        "rank": 79,
        "tag": "TPM",
        "name": "_spawnboy",
        "value": 10284720
      },
      {
        "rank": 80,
        "tag": "",
        "name": "Lil Buddy",
        "value": 10084467
      },
      {
        "rank": 81,
        "tag": "SXY",
        "name": "Natwickley",
        "value": 10077672
      },
      {
        "rank": 82,
        "tag": "",
        "name": "Sigbin",
        "value": 9996827
      },
      {
        "rank": 83,
        "tag": "GLO",
        "name": "AlexTheGreat",
        "value": 9926228
      },
      {
        "rank": 84,
        "tag": "TPM",
        "name": "Lady McCor",
        "value": 9814291
      },
      {
        "rank": 85,
        "tag": "SXY",
        "name": "Elsbethos",
        "value": 9778807
      },
      {
        "rank": 86,
        "tag": "TPM",
        "name": "zazi",
        "value": 9755386
      },
      {
        "rank": 87,
        "tag": "",
        "name": "",
        "value": 9453208
      },
      {
        "rank": 88,
        "tag": "BLD",
        "name": "Lagertha",
        "value": 9453208
      },
      {
        "rank": 89,
        "tag": "",
        "name": "",
        "value": 9446889
      },
      {
        "rank": 90,
        "tag": "",
        "name": "The Duo",
        "value": 9446889
      },
      {
        "rank": 91,
        "tag": "TPM",
        "name": "ABADDY",
        "value": 9343892
      },
      {
        "rank": 92,
        "tag": "",
        "name": "",
        "value": 9308422
      },
      {
        "rank": 93,
        "tag": "TPM",
        "name": "Logantoxtle",
        "value": 9308422
      },
      {
        "rank": 94,
        "tag": "BLD",
        "name": "Holiva",
        "value": 8996780
      },
      {
        "rank": 95,
        "tag": "",
        "name": "",
        "value": 8838885
      },
      {
        "rank": 96,
        "tag": "",
        "name": "Chappie",
        "value": 8838885
      },
      {
        "rank": 97,
        "tag": "HvK",
        "name": "Havok",
        "value": 817265
      },
      {
        "rank": 98,
        "tag": "",
        "name": "Peanut Butter",
        "value": 35391
      },
      {
        "rank": 99,
        "tag": "TPM",
        "name": "Sir Xant",
        "value": 18139
      },
      {
        "rank": 100,
        "tag": "",
        "name": "Kill Count",
        "value": 0
      }
    ],
    "hero_power": [
      {
        "rank": 1,
        "tag": "SXY",
        "name": "Cody4136",
        "value": 19226068
      },
      {
        "rank": 2,
        "tag": "BLD",
        "name": "FeeZPlay",
        "value": 15948062
      },
      {
        "rank": 3,
        "tag": "SXY",
        "name": "The Don Hugo",
        "value": 11688409
      },
      {
        "rank": 4,
        "tag": "HvK",
        "name": "Havok",
        "value": 11128359
      },
      {
        "rank": 5,
        "tag": "",
        "name": "(SXYJZ IY A D",
        "value": 11026427
      },
      {
        "rank": 6,
        "tag": "BLD",
        "name": "Jbrav ST",
        "value": 10865488
      },
      {
        "rank": 7,
        "tag": "TPM",
        "name": "Jxl? Gaara",
        "value": 9475150
      },
      {
        "rank": 8,
        "tag": "",
        "name": "(BLDPups",
        "value": 9369988
      },
      {
        "rank": 9,
        "tag": "",
        "name": "(BLDJGLADIATOR",
        "value": 9111144
      },
      {
        "rank": 10,
        "tag": "TPM",
        "name": "TSnell",
        "value": 8719270
      },
      {
        "rank": 11,
        "tag": "BLD",
        "name": "MiffyOadis",
        "value": 8122199
      },
      {
        "rank": 12,
        "tag": "TPM",
        "name": "Lady Basia",
        "value": 7601215
      },
      {
        "rank": 13,
        "tag": "",
        "name": "Hybrid Stalker",
        "value": 7296562
      },
      {
        "rank": 14,
        "tag": "SXY",
        "name": "kace",
        "value": 7131127
      },
      {
        "rank": 15,
        "tag": "GLO",
        "name": "Foxconn",
        "value": 6975994
      },
      {
        "rank": 16,
        "tag": "BLD",
        "name": "DreadPirateGuntr",
        "value": 6839179
      },
      {
        "rank": 17,
        "tag": "GLO",
        "name": "Compal",
        "value": 6833679
      },
      {
        "rank": 18,
        "tag": "GLO",
        "name": "Compal",
        "value": 6833679
      },
      {
        "rank": 19,
        "tag": "GLO",
        "name": "MadLuck",
        "value": 6263776
      },
      {
        "rank": 20,
        "tag": "SXY",
        "name": "Levi Foxtrott",
        "value": 5919490
      },
      {
        "rank": 21,
        "tag": "BLD",
        "name": "Benimaru",
        "value": 5879332
      },
      {
        "rank": 22,
        "tag": "GLO",
        "name": "PunishmentofGod",
        "value": 5738223
      },
      {
        "rank": 23,
        "tag": "SXY",
        "name": "Kat",
        "value": 5693361
      },
      {
        "rank": 24,
        "tag": "SXY",
        "name": "Bri A genoux",
        "value": 5273190
      },
      {
        "rank": 25,
        "tag": "BLD",
        "name": "Rossi",
        "value": 5226200
      },
      {
        "rank": 26,
        "tag": "TPM",
        "name": "YB 3RR1871FNAL",
        "value": 5182854
      },
      {
        "rank": 27,
        "tag": "BLD",
        "name": "RAZoro",
        "value": 5146524
      },
      {
        "rank": 28,
        "tag": "BLD",
        "name": "TinyPumpkinJojo",
        "value": 5140329
      },
      {
        "rank": 29,
        "tag": "TPM",
        "name": "Blackyy",
        "value": 5070835
      },
      {
        "rank": 30,
        "tag": "BLD",
        "name": "Phlyx",
        "value": 4907495
      },
      {
        "rank": 31,
        "tag": "GLO",
        "name": "AlexTheGreat",
        "value": 4819130
      },
      {
        "rank": 32,
        "tag": "BLD",
        "name": "CrazyNotDead Yet",
        "value": 4707835
      },
      {
        "rank": 33,
        "tag": "TPM",
        "name": "Sir Xant",
        "value": 4685669
      },
      {
        "rank": 34,
        "tag": "BLD",
        "name": "candy",
        "value": 4601260
      },
      {
        "rank": 35,
        "tag": "TPM",
        "name": "Amoebaojo",
        "value": 4531801
      },
      {
        "rank": 36,
        "tag": "SXY",
        "name": "OsTraL",
        "value": 4491813
      },
      {
        "rank": 37,
        "tag": "BLD",
        "name": "KhaosQween?",
        "value": 4483924
      },
      {
        "rank": 38,
        "tag": "TPM",
        "name": "PrincessGold",
        "value": 4474477
      },
      {
        "rank": 39,
        "tag": "SXY",
        "name": "Casanova 777",
        "value": 4472787
      },
      {
        "rank": 40,
        "tag": "TPM",
        "name": "Aidil Sfar",
        "value": 4455878
      },
      {
        "rank": 41,
        "tag": "GLO",
        "name": "johno",
        "value": 4451530
      },
      {
        "rank": 42,
        "tag": "BLD",
        "name": "Sal",
        "value": 4351957
      },
      {
        "rank": 43,
        "tag": "BLD",
        "name": "Jables The Great",
        "value": 4340834
      },
      {
        "rank": 44,
        "tag": "TPM",
        "name": "tmax",
        "value": 4325262
      },
      {
        "rank": 45,
        "tag": "SXY",
        "name": "Robescady",
        "value": 4284335
      },
      {
        "rank": 46,
        "tag": "SXY",
        "name": "T HE MA D KING",
        "value": 4265491
      },
      {
        "rank": 47,
        "tag": "TPM",
        "name": "?IIE e2ZRED ribbon",
        "value": 4248697
      },
      {
        "rank": 48,
        "tag": "GLO",
        "name": "Deltamon",
        "value": 4224482
      },
      {
        "rank": 49,
        "tag": "LIC",
        "name": "EMBERB",
        "value": 4210145
      },
      {
        "rank": 50,
        "tag": "BLD",
        "name": "Grandar",
        "value": 4116335
      },
      {
        "rank": 51,
        "tag": "GLO",
        "name": "Gluck",
        "value": 4093035
      },
      {
        "rank": 52,
        "tag": "GLO",
        "name": "Arthur Dayne",
        "value": 4086341
      },
      {
        "rank": 53,
        "tag": "BLD",
        "name": "Kela",
        "value": 4035184
      },
      {
        "rank": 54,
        "tag": "gLO",
        "name": "NotMad",
        "value": 4027260
      },
      {
        "rank": 55,
        "tag": "SXY",
        "name": "Natwickley",
        "value": 4003412
      },
      {
        "rank": 56,
        "tag": "SXY",
        "name": "Queen Milfshakes",
        "value": 3994547
      },
      {
        "rank": 57,
        "tag": "TPM",
        "name": "Waffle",
        "value": 3962510
      },
      {
        "rank": 58,
        "tag": "TPM",
        "name": "dslsmoke",
        "value": 3956084
      },
      {
        "rank": 59,
        "tag": "TPM",
        "name": "Kenth",
        "value": 3924210
      },
      {
        "rank": 60,
        "tag": "TPM",
        "name": "KKYU_%3",
        "value": 3888568
      },
      {
        "rank": 61,
        "tag": "TPM",
        "name": "Pho Dac Biet",
        "value": 3843535
      },
      {
        "rank": 62,
        "tag": "GLO",
        "name": "JHGE@",
        "value": 3807288
      },
      {
        "rank": 63,
        "tag": "GLO",
        "name": "LITEON",
        "value": 3805315
      },
      {
        "rank": 64,
        "tag": "TPM",
        "name": "AdryBeast",
        "value": 3801302
      },
      {
        "rank": 65,
        "tag": "LIC",
        "name": "-kace",
        "value": 3793035
      },
      {
        "rank": 66,
        "tag": "TPM",
        "name": "_spawnboy",
        "value": 3788942
      },
      {
        "rank": 67,
        "tag": "GLO",
        "name": "Raja",
        "value": 3788555
      },
      {
        "rank": 68,
        "tag": "TPM",
        "name": "Wadyk",
        "value": 3693885
      },
      {
        "rank": 69,
        "tag": "",
        "name": "Bjames3388",
        "value": 3670382
      },
      {
        "rank": 70,
        "tag": "BLD",
        "name": "Mary",
        "value": 3661700
      },
      {
        "rank": 71,
        "tag": "TPM",
        "name": "ABADDY",
        "value": 3661245
      },
      {
        "rank": 72,
        "tag": "BLD",
        "name": "ze7o",
        "value": 3626814
      },
      {
        "rank": 73,
        "tag": "BLD",
        "name": "N45",
        "value": 3624277
      },
      {
        "rank": 74,
        "tag": "TPM",
        "name": "MiloPeng",
        "value": 3608901
      },
      {
        "rank": 75,
        "tag": "BLD",
        "name": "Zelem",
        "value": 3575440
      },
      {
        "rank": 76,
        "tag": "GLO",
        "name": "Ennoconn",
        "value": 3566510
      },
      {
        "rank": 77,
        "tag": "SXY",
        "name": "Gardale",
        "value": 3554785
      },
      {
        "rank": 78,
        "tag": "",
        "name": "Blaze",
        "value": 3541110
      },
      {
        "rank": 79,
        "tag": "SXY",
        "name": "EIsbethos",
        "value": 3517452
      },
      {
        "rank": 80,
        "tag": "BLD",
        "name": "Denyut Denyut",
        "value": 3516955
      },
      {
        "rank": 81,
        "tag": "SXY",
        "name": "Maple",
        "value": 3506002
      },
      {
        "rank": 82,
        "tag": "BLD",
        "name": "Rashmi",
        "value": 3495780
      },
      {
        "rank": 83,
        "tag": "SXY",
        "name": "IBad blood",
        "value": 3474250
      },
      {
        "rank": 84,
        "tag": "SXY",
        "name": "Romulus",
        "value": 3453593
      },
      {
        "rank": 85,
        "tag": "TPM",
        "name": "LobaTheCute",
        "value": 3450545
      },
      {
        "rank": 86,
        "tag": "",
        "name": "Hero: Petra",
        "value": 3450545
      },
      {
        "rank": 87,
        "tag": "GLO",
        "name": "Lks",
        "value": 3448100
      },
      {
        "rank": 88,
        "tag": "SXY",
        "name": "Popcorn Colonel",
        "value": 3445242
      },
      {
        "rank": 89,
        "tag": "SXY",
        "name": "Non",
        "value": 3440460
      },
      {
        "rank": 90,
        "tag": "SXY",
        "name": "INon",
        "value": 3440460
      },
      {
        "rank": 91,
        "tag": "LIc",
        "name": "Lil Kat",
        "value": 3438874
      },
      {
        "rank": 92,
        "tag": "TPM",
        "name": "e JHG",
        "value": 3433677
      },
      {
        "rank": 93,
        "tag": "TPM",
        "name": "JnHG",
        "value": 3433677
      },
      {
        "rank": 94,
        "tag": "TPM",
        "name": "JJHE",
        "value": 3433677
      },
      {
        "rank": 95,
        "tag": "TPM",
        "name": "e hs",
        "value": 3433677
      },
      {
        "rank": 96,
        "tag": "TPM",
        "name": "Jnl#",
        "value": 3433677
      },
      {
        "rank": 97,
        "tag": "TPM",
        "name": "zazi",
        "value": 3427709
      },
      {
        "rank": 98,
        "tag": "TPM",
        "name": "Two More Beers",
        "value": 3416230
      },
      {
        "rank": 99,
        "tag": "",
        "name": "Peanut Butter",
        "value": 31040
      },
      {
        "rank": 100,
        "tag": "",
        "name": "Hero Power",
        "value": 0
      }
    ],
    "heros_total_power": [
      {
        "rank": 1,
        "tag": "SXY",
        "name": "Cody4136",
        "value": 98737688
      },
      {
        "rank": 2,
        "tag": "BLD",
        "name": "FeeZPlay",
        "value": 72714091
      },
      {
        "rank": 3,
        "tag": "sxY",
        "name": "The Don Hugo",
        "value": 61291482
      },
      {
        "rank": 4,
        "tag": "HvK",
        "name": "Havok",
        "value": 60202479
      },
      {
        "rank": 5,
        "tag": "TPM",
        "name": "TSnell",
        "value": 59906791
      },
      {
        "rank": 6,
        "tag": "",
        "name": "SxYJZ IY A D",
        "value": 57372842
      },
      {
        "rank": 7,
        "tag": "BLD",
        "name": "GLADIATOR",
        "value": 56022638
      },
      {
        "rank": 8,
        "tag": "BLD",
        "name": "Jbrav ST",
        "value": 53759494
      },
      {
        "rank": 9,
        "tag": "BLD",
        "name": "Jbrav ST",
        "value": 53759494
      },
      {
        "rank": 10,
        "tag": "TPM",
        "name": "Lady Basia",
        "value": 53473700
      },
      {
        "rank": 11,
        "tag": "",
        "name": "XBLDJPups",
        "value": 51589319
      },
      {
        "rank": 12,
        "tag": "TPM",
        "name": "Aidil Sfar",
        "value": 45236964
      },
      {
        "rank": 13,
        "tag": "SXY",
        "name": "kace",
        "value": 43091069
      },
      {
        "rank": 14,
        "tag": "GLO",
        "name": "PunishmentofGod",
        "value": 42102499
      },
      {
        "rank": 15,
        "tag": "BLD",
        "name": "DreadPirateGuntr",
        "value": 41373834
      },
      {
        "rank": 16,
        "tag": "GLO",
        "name": "AlexTheGreat",
        "value": 39320906
      },
      {
        "rank": 17,
        "tag": "SXY",
        "name": "Levi Foxtrott",
        "value": 39165406
      },
      {
        "rank": 18,
        "tag": "TPM",
        "name": "ABADDY",
        "value": 39147280
      },
      {
        "rank": 19,
        "tag": "SXY",
        "name": "Natwickley",
        "value": 38760103
      },
      {
        "rank": 20,
        "tag": "SXY",
        "name": "GovRaden",
        "value": 38707541
      },
      {
        "rank": 21,
        "tag": "TPM",
        "name": "Lady McCor",
        "value": 38646648
      },
      {
        "rank": 22,
        "tag": "GLO",
        "name": "Foxconn",
        "value": 38543213
      },
      {
        "rank": 23,
        "tag": "TPM",
        "name": "Double A",
        "value": 38245437
      },
      {
        "rank": 24,
        "tag": "TPM",
        "name": "Blackyy",
        "value": 38206253
      },
      {
        "rank": 25,
        "tag": "TPM",
        "name": "Lady Fiddlestix",
        "value": 37167044
      },
      {
        "rank": 26,
        "tag": "BLD",
        "name": "Ambrother",
        "value": 36595207
      },
      {
        "rank": 27,
        "tag": "BLD",
        "name": "Rossi",
        "value": 36387439
      },
      {
        "rank": 28,
        "tag": "BLD",
        "name": "Callisto",
        "value": 36258965
      },
      {
        "rank": 29,
        "tag": "TP",
        "name": "MiYB 3661E76Tn RL",
        "value": 36143806
      },
      {
        "rank": 30,
        "tag": "BLD",
        "name": "Ragnar Lothbrok",
        "value": 35729069
      },
      {
        "rank": 31,
        "tag": "GLO",
        "name": "MadLuck",
        "value": 35423205
      },
      {
        "rank": 32,
        "tag": "SXY",
        "name": "Bri A genoux",
        "value": 35342593
      },
      {
        "rank": 33,
        "tag": "TPM",
        "name": "Pho Dac Biet",
        "value": 34935886
      },
      {
        "rank": 34,
        "tag": "BLD",
        "name": "TinyPumpkin Jojo",
        "value": 34651718
      },
      {
        "rank": 35,
        "tag": "Kor",
        "name": "EF4_okx",
        "value": 34474086
      },
      {
        "rank": 36,
        "tag": "GLO",
        "name": "Green Monster",
        "value": 34371293
      },
      {
        "rank": 37,
        "tag": "TPM",
        "name": "Waffle",
        "value": 34267810
      },
      {
        "rank": 38,
        "tag": "BLD",
        "name": "CrazyNotDeadYet",
        "value": 34152858
      },
      {
        "rank": 39,
        "tag": "TPM",
        "name": "Aiman Sfar",
        "value": 33734007
      },
      {
        "rank": 40,
        "tag": "TPM",
        "name": "Duke Promethean",
        "value": 33697489
      },
      {
        "rank": 41,
        "tag": "SXY",
        "name": "Queen Milfshakes",
        "value": 33427606
      },
      {
        "rank": 42,
        "tag": "TPM",
        "name": "LobaTheCute",
        "value": 33397055
      },
      {
        "rank": 43,
        "tag": "TPM",
        "name": "Clark",
        "value": 33248416
      },
      {
        "rank": 44,
        "tag": "GLO",
        "name": "Arthur Dayne",
        "value": 33104239
      },
      {
        "rank": 45,
        "tag": "SXY",
        "name": "Master Kosha",
        "value": 33081337
      },
      {
        "rank": 46,
        "tag": "SXY",
        "name": "IBad blood",
        "value": 33076963
      },
      {
        "rank": 47,
        "tag": "BLD",
        "name": "Sal",
        "value": 32980858
      },
      {
        "rank": 48,
        "tag": "GLO",
        "name": "Deltamon",
        "value": 32916042
      },
      {
        "rank": 49,
        "tag": "TPM",
        "name": "PrincessGold",
        "value": 32901875
      },
      {
        "rank": 50,
        "tag": "TPM",
        "name": "tmax",
        "value": 32811529
      },
      {
        "rank": 51,
        "tag": "TPM",
        "name": "dslsmoke",
        "value": 32729565
      },
      {
        "rank": 52,
        "tag": "SXY",
        "name": "Lonelyman",
        "value": 32660876
      },
      {
        "rank": 53,
        "tag": "BLD",
        "name": "ChrisKang1592",
        "value": 32498992
      },
      {
        "rank": 54,
        "tag": "BLD",
        "name": "N45",
        "value": 32488148
      },
      {
        "rank": 55,
        "tag": "TPM",
        "name": "_spawnboy",
        "value": 32447444
      },
      {
        "rank": 56,
        "tag": "BLD",
        "name": "Denyut Denyut",
        "value": 32403605
      },
      {
        "rank": 57,
        "tag": "GLO",
        "name": "MB E@",
        "value": 32383864
      },
      {
        "rank": 58,
        "tag": "GLO",
        "name": "vts",
        "value": 32244264
      },
      {
        "rank": 59,
        "tag": "SXY",
        "name": "Maple",
        "value": 32171049
      },
      {
        "rank": 60,
        "tag": "SF0j2",
        "name": "15=",
        "value": 32052151
      },
      {
        "rank": 61,
        "tag": "BLD",
        "name": "saniku",
        "value": 32028859
      },
      {
        "rank": 62,
        "tag": "",
        "name": "Dead",
        "value": 31883159
      },
      {
        "rank": 63,
        "tag": "TPM",
        "name": "AdryBeast",
        "value": 31862948
      },
      {
        "rank": 64,
        "tag": "BLD",
        "name": "KhaosQween?",
        "value": 31697743
      },
      {
        "rank": 65,
        "tag": "BLD",
        "name": "Tipsy",
        "value": 31597228
      },
      {
        "rank": 66,
        "tag": "TPM",
        "name": "Volur",
        "value": 31450722
      },
      {
        "rank": 67,
        "tag": "TPM",
        "name": "RUMhR",
        "value": 31413876
      },
      {
        "rank": 68,
        "tag": "BLD",
        "name": "Taz Man",
        "value": 31404763
      },
      {
        "rank": 69,
        "tag": "GLO",
        "name": "sabbiolina",
        "value": 31239607
      },
      {
        "rank": 70,
        "tag": "BLD",
        "name": "Kela",
        "value": 31173307
      },
      {
        "rank": 71,
        "tag": "SXY",
        "name": "IRobescady",
        "value": 30997408
      },
      {
        "rank": 72,
        "tag": "BLD",
        "name": "Holiva",
        "value": 30936763
      },
      {
        "rank": 73,
        "tag": "TPM",
        "name": "Kenth",
        "value": 30684550
      },
      {
        "rank": 74,
        "tag": "",
        "name": "Bullzeye",
        "value": 30619514
      },
      {
        "rank": 75,
        "tag": "GLO",
        "name": "Raja",
        "value": 30431754
      },
      {
        "rank": 76,
        "tag": "GLO",
        "name": "Radamanthys",
        "value": 30429793
      },
      {
        "rank": 77,
        "tag": "GLo",
        "name": "j-7223",
        "value": 30249268
      },
      {
        "rank": 78,
        "tag": "TPM",
        "name": "Fawaz",
        "value": 30181214
      },
      {
        "rank": 79,
        "tag": "TPM",
        "name": "Odysseus13",
        "value": 30156421
      },
      {
        "rank": 80,
        "tag": "GLO",
        "name": "#219Sam",
        "value": 29969669
      },
      {
        "rank": 81,
        "tag": "",
        "name": "",
        "value": 29837664
      },
      {
        "rank": 82,
        "tag": "",
        "name": "",
        "value": 29835187
      },
      {
        "rank": 83,
        "tag": "SXY",
        "name": "Ypgatra",
        "value": 29835187
      },
      {
        "rank": 84,
        "tag": "GL",
        "name": "Oljohno",
        "value": 29767932
      },
      {
        "rank": 85,
        "tag": "GLo",
        "name": "johno",
        "value": 29767932
      },
      {
        "rank": 86,
        "tag": "GLo",
        "name": "ljohno",
        "value": 29767932
      },
      {
        "rank": 87,
        "tag": "BLD",
        "name": "Benimaru",
        "value": 29661792
      },
      {
        "rank": 88,
        "tag": "SXY",
        "name": "IGREAT CORNHOLIO",
        "value": 29531918
      },
      {
        "rank": 89,
        "tag": "SXY",
        "name": "GREAT CORNHOLIO",
        "value": 29531918
      },
      {
        "rank": 90,
        "tag": "GLO",
        "name": "AKZ",
        "value": 29518627
      },
      {
        "rank": 91,
        "tag": "GLO",
        "name": "Lord_Spin",
        "value": 29504991
      },
      {
        "rank": 92,
        "tag": "SXY",
        "name": "Casanova 777",
        "value": 29495328
      },
      {
        "rank": 93,
        "tag": "BLD",
        "name": "ze7o",
        "value": 662313
      },
      {
        "rank": 94,
        "tag": "BLD",
        "name": "MiffyOadis",
        "value": 158551
      },
      {
        "rank": 95,
        "tag": "",
        "name": "Peanut Butter",
        "value": 65630
      },
      {
        "rank": 96,
        "tag": "TPM",
        "name": "JI? Gaara",
        "value": 57269
      },
      {
        "rank": 97,
        "tag": "",
        "name": "Hero's Total Power",
        "value": 0
      },
      {
        "rank": 98,
        "tag": "",
        "name": "Govelnor",
        "value": 0
      },
      {
        "rank": 99,
        "tag": "",
        "name": "Herob Tot-Powcr",
        "value": 0
      },
      {
        "rank": 100,
        "tag": "",
        "name": "Iclolca~",
        "value": 0
      }
    ],
    "total_pet_power": [
      {
        "rank": 1,
        "tag": "SXY",
        "name": "Cody4136",
        "value": 24928440
      },
      {
        "rank": 2,
        "tag": "BLD",
        "name": "FeeZPlay",
        "value": 22821360
      },
      {
        "rank": 3,
        "tag": "HvK",
        "name": "Havok",
        "value": 21664560
      },
      {
        "rank": 4,
        "tag": "",
        "name": "SXYJZ IY A D",
        "value": 18803400
      },
      {
        "rank": 5,
        "tag": "TPM",
        "name": "Lady Basia",
        "value": 18564600
      },
      {
        "rank": 6,
        "tag": "",
        "name": "Hybrid Stalker",
        "value": 18501600
      },
      {
        "rank": 7,
        "tag": "TPM",
        "name": "JI? Gaara",
        "value": 18443520
      },
      {
        "rank": 8,
        "tag": "TPM",
        "name": "TSnell",
        "value": 18376080
      },
      {
        "rank": 9,
        "tag": "SXY",
        "name": "Maple",
        "value": 18318360
      },
      {
        "rank": 10,
        "tag": "BLD",
        "name": "Jbrav ST",
        "value": 18286800
      },
      {
        "rank": 11,
        "tag": "BLD",
        "name": "GLADIATOR",
        "value": 18015600
      },
      {
        "rank": 12,
        "tag": "BLD",
        "name": "Rossi",
        "value": 17970480
      },
      {
        "rank": 13,
        "tag": "SXY",
        "name": "The Don Hugo",
        "value": 17933400
      },
      {
        "rank": 14,
        "tag": "SXY",
        "name": "Bri A genoux",
        "value": 17856240
      },
      {
        "rank": 15,
        "tag": "SXY",
        "name": "Levi Foxtrott",
        "value": 17832360
      },
      {
        "rank": 16,
        "tag": "SXY",
        "name": "Kat",
        "value": 17728560
      },
      {
        "rank": 17,
        "tag": "TPM",
        "name": "LobaTheCute",
        "value": 17217360
      },
      {
        "rank": 18,
        "tag": "BLD",
        "name": "MiffyOadis",
        "value": 17104560
      },
      {
        "rank": 19,
        "tag": "BLD",
        "name": "DreadPirateGuntr",
        "value": 17102280
      },
      {
        "rank": 20,
        "tag": "SXY",
        "name": "kace",
        "value": 17056560
      },
      {
        "rank": 21,
        "tag": "GLO",
        "name": "PunishmentofGod",
        "value": 16975440
      },
      {
        "rank": 22,
        "tag": "BLD",
        "name": "Phlyx",
        "value": 16905240
      },
      {
        "rank": 23,
        "tag": "BLD",
        "name": "Pups",
        "value": 16829640
      },
      {
        "rank": 24,
        "tag": "TPM",
        "name": "Volur",
        "value": 16819320
      },
      {
        "rank": 25,
        "tag": "TPM",
        "name": "Pho Dac Biet",
        "value": 16563360
      },
      {
        "rank": 26,
        "tag": "BLD",
        "name": "TinyPumpkin Jojo",
        "value": 16490160
      },
      {
        "rank": 27,
        "tag": "GLO",
        "name": "Yniss",
        "value": 16466640
      },
      {
        "rank": 28,
        "tag": "TPM",
        "name": "Duke Promethean",
        "value": 16446720
      },
      {
        "rank": 29,
        "tag": "BLD",
        "name": "Taz Man",
        "value": 16357080
      },
      {
        "rank": 30,
        "tag": "TPM",
        "name": "Blackyy",
        "value": 16303800
      },
      {
        "rank": 31,
        "tag": "SXY",
        "name": "Lonelyman",
        "value": 16238640
      },
      {
        "rank": 32,
        "tag": "GL",
        "name": "Olvts",
        "value": 16220280
      },
      {
        "rank": 33,
        "tag": "TPM",
        "name": "_spawnboy",
        "value": 16194600
      },
      {
        "rank": 34,
        "tag": "TPM",
        "name": "zI= 22ZRED ribbon",
        "value": 16163400
      },
      {
        "rank": 35,
        "tag": "TPM",
        "name": "dslsmoke",
        "value": 16162800
      },
      {
        "rank": 36,
        "tag": "SXY",
        "name": "GovRaden",
        "value": 16150560
      },
      {
        "rank": 37,
        "tag": "GLO",
        "name": "Foxconn",
        "value": 16056120
      },
      {
        "rank": 38,
        "tag": "BLD",
        "name": "saniku",
        "value": 16022280
      },
      {
        "rank": 39,
        "tag": "BLD",
        "name": "Sal",
        "value": 16017480
      },
      {
        "rank": 40,
        "tag": "TPM",
        "name": "Double A",
        "value": 15991800
      },
      {
        "rank": 41,
        "tag": "BLD",
        "name": "Mawi",
        "value": 15979560
      },
      {
        "rank": 42,
        "tag": "JIB",
        "name": "Muddywan",
        "value": 15978360
      },
      {
        "rank": 43,
        "tag": "gLo",
        "name": "NotMad",
        "value": 15975240
      },
      {
        "rank": 44,
        "tag": "SXY",
        "name": "ITERA",
        "value": 15958440
      },
      {
        "rank": 45,
        "tag": "",
        "name": "Dead",
        "value": 15920880
      },
      {
        "rank": 46,
        "tag": "SXY",
        "name": "Elsbethos",
        "value": 15891000
      },
      {
        "rank": 47,
        "tag": "SXY",
        "name": "demon lord",
        "value": 15885000
      },
      {
        "rank": 48,
        "tag": "GLO",
        "name": "Ergamaa",
        "value": 15874800
      },
      {
        "rank": 49,
        "tag": "TPM",
        "name": "Aidil Sfar",
        "value": 15846840
      },
      {
        "rank": 50,
        "tag": "TPM",
        "name": "Sir Xant",
        "value": 15835200
      },
      {
        "rank": 51,
        "tag": "GLO",
        "name": "Arthur Dayne",
        "value": 15820440
      },
      {
        "rank": 52,
        "tag": "SXY",
        "name": "IGame6Klay",
        "value": 15803040
      },
      {
        "rank": 53,
        "tag": "BLD",
        "name": "Zelem",
        "value": 15784320
      },
      {
        "rank": 54,
        "tag": "TPM",
        "name": "tmax",
        "value": 15779280
      },
      {
        "rank": 55,
        "tag": "TPM",
        "name": "Lady McCor",
        "value": 15754920
      },
      {
        "rank": 56,
        "tag": "TPM",
        "name": "Waffle",
        "value": 15747120
      },
      {
        "rank": 57,
        "tag": "Kor",
        "name": "??lol8",
        "value": 15743520
      },
      {
        "rank": 58,
        "tag": "GLo",
        "name": "j-7423",
        "value": 15723600
      },
      {
        "rank": 59,
        "tag": "GLO",
        "name": "AKZ",
        "value": 15703440
      },
      {
        "rank": 60,
        "tag": "BLD",
        "name": "CrazyNotDead Yet",
        "value": 15662520
      },
      {
        "rank": 61,
        "tag": "GLO",
        "name": "JJI#E*",
        "value": 15630720
      },
      {
        "rank": 62,
        "tag": "GLO",
        "name": "Raja",
        "value": 15628680
      },
      {
        "rank": 63,
        "tag": "GLO",
        "name": "BHE LAT MHO",
        "value": 15628080
      },
      {
        "rank": 64,
        "tag": "TPM",
        "name": "Ed1",
        "value": 15577920
      },
      {
        "rank": 65,
        "tag": "TPM",
        "name": "ss",
        "value": 15563880
      },
      {
        "rank": 66,
        "tag": "GLO",
        "name": "Jandel",
        "value": 15553200
      },
      {
        "rank": 67,
        "tag": "JIB",
        "name": "Tynke",
        "value": 15539640
      },
      {
        "rank": 68,
        "tag": "BLD",
        "name": "Kela",
        "value": 15529920
      },
      {
        "rank": 69,
        "tag": "GLo",
        "name": "Teteyutu",
        "value": 15526200
      },
      {
        "rank": 70,
        "tag": "BLD",
        "name": "RAZoro",
        "value": 15514920
      },
      {
        "rank": 71,
        "tag": "TPM",
        "name": "J JnJHG",
        "value": 15501240
      },
      {
        "rank": 72,
        "tag": "TPM",
        "name": "KImtTK",
        "value": 15500400
      },
      {
        "rank": 73,
        "tag": "",
        "name": "",
        "value": 15493200
      },
      {
        "rank": 74,
        "tag": "TPM",
        "name": "Kikokikohoho",
        "value": 15483240
      },
      {
        "rank": 75,
        "tag": "SXY",
        "name": "Casanova 777",
        "value": 15477600
      },
      {
        "rank": 76,
        "tag": "SXY",
        "name": "Wemly",
        "value": 15465480
      },
      {
        "rank": 77,
        "tag": "GLO",
        "name": "pk556",
        "value": 15462720
      },
      {
        "rank": 78,
        "tag": "TPM",
        "name": "Dipset",
        "value": 15435000
      },
      {
        "rank": 79,
        "tag": "TPM",
        "name": "Clark",
        "value": 15410760
      },
      {
        "rank": 80,
        "tag": "SXY",
        "name": "jane",
        "value": 15410760
      },
      {
        "rank": 81,
        "tag": "BLD",
        "name": "ze7o",
        "value": 15401640
      },
      {
        "rank": 82,
        "tag": "BLD",
        "name": "Casira",
        "value": 15400080
      },
      {
        "rank": 83,
        "tag": "SXY",
        "name": "Gardale",
        "value": 15391560
      },
      {
        "rank": 84,
        "tag": "TP",
        "name": "Miyb 3 RRTenmTAWL",
        "value": 15384000
      },
      {
        "rank": 85,
        "tag": "SXY",
        "name": "Zerglord",
        "value": 15366600
      },
      {
        "rank": 86,
        "tag": "GLO",
        "name": "Deltamon",
        "value": 15360840
      },
      {
        "rank": 87,
        "tag": "GLO",
        "name": "Scottysham",
        "value": 15355320
      },
      {
        "rank": 88,
        "tag": "",
        "name": "",
        "value": 15349080
      },
      {
        "rank": 89,
        "tag": "TPM",
        "name": "spiderqueen",
        "value": 15349080
      },
      {
        "rank": 90,
        "tag": "SXY",
        "name": "Master Kosha",
        "value": 15334800
      },
      {
        "rank": 91,
        "tag": "TPM",
        "name": "Aiman Sfar",
        "value": 15334200
      },
      {
        "rank": 92,
        "tag": "GLO",
        "name": "Compal",
        "value": 15331080
      },
      {
        "rank": 93,
        "tag": "GLO",
        "name": "Compal",
        "value": 15331080
      },
      {
        "rank": 94,
        "tag": "GLo",
        "name": "Compal",
        "value": 15331080
      },
      {
        "rank": 95,
        "tag": "SXY",
        "name": "Ypgatra",
        "value": 15330360
      },
      {
        "rank": 96,
        "tag": "GLO",
        "name": "Tinybluman",
        "value": 15305160
      },
      {
        "rank": 97,
        "tag": "GLO",
        "name": "JBoasim",
        "value": 15302280
      },
      {
        "rank": 98,
        "tag": "",
        "name": "Peanut Butter",
        "value": 35388
      },
      {
        "rank": 99,
        "tag": "",
        "name": "Total Pet Power",
        "value": 0
      },
      {
        "rank": 100,
        "tag": "",
        "name": "Govelnor",
        "value": 0
      }
    ],
    "mystic_trial": [
      {
        "rank": 1,
        "tag": "SXY",
        "name": "Cody4136",
        "value": 2511
      },
      {
        "rank": 2,
        "tag": "BLD",
        "name": "FeeZPlay",
        "value": 2473
      },
      {
        "rank": 3,
        "tag": "HvK",
        "name": "Havok",
        "value": 2346
      },
      {
        "rank": 4,
        "tag": "SXY",
        "name": "IZIY A D",
        "value": 2193
      },
      {
        "rank": 5,
        "tag": "SXY",
        "name": "The Don Hugo",
        "value": 2122
      },
      {
        "rank": 6,
        "tag": "TPM",
        "name": "4xI? Gaara",
        "value": 2110
      },
      {
        "rank": 7,
        "tag": "BLD",
        "name": "Jbrav ST",
        "value": 2100
      },
      {
        "rank": 8,
        "tag": "BLD",
        "name": "Pups",
        "value": 2072
      },
      {
        "rank": 9,
        "tag": "BLD",
        "name": "GLADIATOR",
        "value": 2025
      },
      {
        "rank": 10,
        "tag": "",
        "name": "XBLDJGLADIATOR",
        "value": 2025
      },
      {
        "rank": 11,
        "tag": "TPM",
        "name": "Lady Basia",
        "value": 2002
      },
      {
        "rank": 12,
        "tag": "BLD",
        "name": "MiffyOadis",
        "value": 1993
      },
      {
        "rank": 13,
        "tag": "TPM",
        "name": "TSnell",
        "value": 1963
      },
      {
        "rank": 14,
        "tag": "SXY",
        "name": "kace",
        "value": 1763
      },
      {
        "rank": 15,
        "tag": "GLO",
        "name": "Foxconn",
        "value": 1762
      },
      {
        "rank": 16,
        "tag": "TPM",
        "name": "Aidil Sfar",
        "value": 1750
      },
      {
        "rank": 17,
        "tag": "BLD",
        "name": "Phlyx",
        "value": 1747
      },
      {
        "rank": 18,
        "tag": "BLD",
        "name": "DreadPirateGuntr",
        "value": 1745
      },
      {
        "rank": 19,
        "tag": "GLO",
        "name": "PunishmentofGod",
        "value": 1653
      },
      {
        "rank": 20,
        "tag": "SXY",
        "name": "Kat",
        "value": 1652
      },
      {
        "rank": 21,
        "tag": "SXY",
        "name": "Levi Foxtrott",
        "value": 1643
      },
      {
        "rank": 22,
        "tag": "TPM",
        "name": "Blackyy",
        "value": 1626
      },
      {
        "rank": 23,
        "tag": "",
        "name": "Hybrid Stalker",
        "value": 1615
      },
      {
        "rank": 24,
        "tag": "BLD",
        "name": "Rossi",
        "value": 1601
      },
      {
        "rank": 25,
        "tag": "GLO",
        "name": "MadLuck",
        "value": 1601
      },
      {
        "rank": 26,
        "tag": "TPM",
        "name": "Double A",
        "value": 1600
      },
      {
        "rank": 27,
        "tag": "TPM",
        "name": "Sir Xant",
        "value": 1581
      },
      {
        "rank": 28,
        "tag": "SXY",
        "name": "Natwickley",
        "value": 1542
      },
      {
        "rank": 29,
        "tag": "SXY",
        "name": "Bri A genoux",
        "value": 1528
      },
      {
        "rank": 30,
        "tag": "BLD",
        "name": "Ambrother",
        "value": 1508
      },
      {
        "rank": 31,
        "tag": "TPM",
        "name": "Waffle",
        "value": 1483
      },
      {
        "rank": 32,
        "tag": "GLO",
        "name": "Deltamon",
        "value": 1480
      },
      {
        "rank": 33,
        "tag": "BLD",
        "name": "Sal",
        "value": 1479
      },
      {
        "rank": 34,
        "tag": "",
        "name": "(TPMiyb ? GRtotm rnwL",
        "value": 1472
      },
      {
        "rank": 35,
        "tag": "GLO",
        "name": "Arthur Dayne",
        "value": 1459
      },
      {
        "rank": 36,
        "tag": "BLD",
        "name": "Callisto",
        "value": 1457
      },
      {
        "rank": 37,
        "tag": "TPM",
        "name": "ABADDY",
        "value": 1452
      },
      {
        "rank": 38,
        "tag": "TPM",
        "name": "Pho Dac Biet",
        "value": 1450
      },
      {
        "rank": 39,
        "tag": "BLD",
        "name": "CrazyNotDeadYet",
        "value": 1447
      },
      {
        "rank": 40,
        "tag": "TPM",
        "name": "2IIE 22ZRED ribbon",
        "value": 1447
      },
      {
        "rank": 41,
        "tag": "SXY",
        "name": "Queen Milfshakes",
        "value": 1444
      },
      {
        "rank": 42,
        "tag": "SXY",
        "name": "Maple",
        "value": 1424
      },
      {
        "rank": 43,
        "tag": "BLD",
        "name": "Kela",
        "value": 1418
      },
      {
        "rank": 44,
        "tag": "SXY",
        "name": "GovRaden",
        "value": 1414
      },
      {
        "rank": 45,
        "tag": "TPM",
        "name": "Marko 73",
        "value": 1411
      },
      {
        "rank": 46,
        "tag": "TPM",
        "name": "tmax",
        "value": 1408
      },
      {
        "rank": 47,
        "tag": "BLD",
        "name": "candy",
        "value": 1402
      },
      {
        "rank": 48,
        "tag": "TPM",
        "name": "dslsmoke",
        "value": 1402
      },
      {
        "rank": 49,
        "tag": "TPM",
        "name": "Volur",
        "value": 1391
      },
      {
        "rank": 50,
        "tag": "TPM",
        "name": "Aiman Sfar",
        "value": 1376
      },
      {
        "rank": 51,
        "tag": "TPM",
        "name": "Lady Fiddlestix",
        "value": 1373
      },
      {
        "rank": 52,
        "tag": "",
        "name": "IBLDJKhaosQween?",
        "value": 1368
      },
      {
        "rank": 53,
        "tag": "TPM",
        "name": "PrincessGold",
        "value": 1367
      },
      {
        "rank": 54,
        "tag": "GLO",
        "name": "Yniss",
        "value": 1366
      },
      {
        "rank": 55,
        "tag": "BLD",
        "name": "Tipsy",
        "value": 1365
      },
      {
        "rank": 56,
        "tag": "TPM",
        "name": "Duke Promethean",
        "value": 1364
      },
      {
        "rank": 57,
        "tag": "BLD",
        "name": "Grandar",
        "value": 1360
      },
      {
        "rank": 58,
        "tag": "SXY",
        "name": "Casanova 777",
        "value": 1360
      },
      {
        "rank": 59,
        "tag": "GL",
        "name": "Olvts",
        "value": 1358
      },
      {
        "rank": 60,
        "tag": "SXY",
        "name": "Lonelyman",
        "value": 1357
      },
      {
        "rank": 61,
        "tag": "TPM",
        "name": "Wadyk",
        "value": 1352
      },
      {
        "rank": 62,
        "tag": "GLO",
        "name": "lH# E@",
        "value": 1350
      },
      {
        "rank": 63,
        "tag": "TPM",
        "name": "Kenth",
        "value": 1345
      },
      {
        "rank": 64,
        "tag": "SXY",
        "name": "Bad blood",
        "value": 1339
      },
      {
        "rank": 65,
        "tag": "SXY",
        "name": "Gardale",
        "value": 1339
      },
      {
        "rank": 66,
        "tag": "TPM",
        "name": "_spawnboy",
        "value": 1334
      },
      {
        "rank": 67,
        "tag": "SXY",
        "name": "Robescady",
        "value": 1334
      },
      {
        "rank": 68,
        "tag": "BLD",
        "name": "Jables The Great",
        "value": 1331
      },
      {
        "rank": 69,
        "tag": "TPM",
        "name": "Logantoxtle",
        "value": 1331
      },
      {
        "rank": 70,
        "tag": "TPM",
        "name": "Amoeba Jojo",
        "value": 1331
      },
      {
        "rank": 71,
        "tag": "BLD",
        "name": "Taz Man",
        "value": 1329
      },
      {
        "rank": 72,
        "tag": "BLD",
        "name": "ze 7o",
        "value": 1314
      },
      {
        "rank": 73,
        "tag": "BLD",
        "name": "RAZoro",
        "value": 1301
      },
      {
        "rank": 74,
        "tag": "GLO",
        "name": "AKZ",
        "value": 1291
      },
      {
        "rank": 75,
        "tag": "TPM",
        "name": "KKYU_%H3",
        "value": 1289
      },
      {
        "rank": 76,
        "tag": "BLD",
        "name": "N45",
        "value": 1289
      },
      {
        "rank": 77,
        "tag": "GLO",
        "name": "Raja",
        "value": 1287
      },
      {
        "rank": 78,
        "tag": "GLO",
        "name": "Radamanthys",
        "value": 1278
      },
      {
        "rank": 79,
        "tag": "SXY",
        "name": "Non",
        "value": 1277
      },
      {
        "rank": 80,
        "tag": "GLO",
        "name": "johno",
        "value": 1277
      },
      {
        "rank": 81,
        "tag": "TPM",
        "name": "Kikokikohoho",
        "value": 1276
      },
      {
        "rank": 82,
        "tag": "SXY",
        "name": "Elsbethos",
        "value": 1265
      },
      {
        "rank": 83,
        "tag": "SXY",
        "name": "Popcorn Colonel",
        "value": 1261
      },
      {
        "rank": 84,
        "tag": "TPM",
        "name": "Clark",
        "value": 1261
      },
      {
        "rank": 85,
        "tag": "Kor",
        "name": "utYzolx",
        "value": 1259
      },
      {
        "rank": 86,
        "tag": "BLD",
        "name": "Casira",
        "value": 1258
      },
      {
        "rank": 87,
        "tag": "SXY",
        "name": "Spartan",
        "value": 1255
      },
      {
        "rank": 88,
        "tag": "TPM",
        "name": "LobaTheCute",
        "value": 1252
      },
      {
        "rank": 89,
        "tag": "TPM",
        "name": "Loba TheCute",
        "value": 1252
      },
      {
        "rank": 90,
        "tag": "",
        "name": "JBLDJDenyut Denyut",
        "value": 1250
      },
      {
        "rank": 91,
        "tag": "BLD",
        "name": "Denyut Denyut",
        "value": 1250
      },
      {
        "rank": 92,
        "tag": "IJBLD",
        "name": "Denyut Denyut",
        "value": 1250
      },
      {
        "rank": 93,
        "tag": "SXY",
        "name": "Master Kosha",
        "value": 1243
      },
      {
        "rank": 94,
        "tag": "SXY",
        "name": "OsTraL",
        "value": 1242
      },
      {
        "rank": 95,
        "tag": "GLO",
        "name": "Teteyutu",
        "value": 1241
      },
      {
        "rank": 96,
        "tag": "GLO",
        "name": "Ennoconn",
        "value": 1241
      },
      {
        "rank": 97,
        "tag": "GLo",
        "name": "Teteyutu",
        "value": 1241
      },
      {
        "rank": 98,
        "tag": "TPM",
        "name": "RUMAR",
        "value": 1235
      },
      {
        "rank": 99,
        "tag": "TPM",
        "name": "RMAR",
        "value": 1235
      },
      {
        "rank": 100,
        "tag": "TPM",
        "name": "RMhLR",
        "value": 1235
      }
    ]
  }
}